googlenewsdecoder/__init__.py
googlenewsdecoder/decoderv1.py
googlenewsdecoder/decoderv2.py
googlenewsdecoder/decoderv3.py
googlenewsdecoder/decoderv4.py
googlenewsdecoder/new_decoderv1.py
googlenewsdecoder-0.1.5.dist-info/LICENSE
googlenewsdecoder-0.1.5.dist-info/METADATA
googlenewsdecoder-0.1.5.dist-info/WHEEL
googlenewsdecoder-0.1.5.dist-info/top_level.txt
googlenewsdecoder-0.1.5.dist-info/RECORD
