Metadata-Version: 2.1
Name: googlenewsdecoder
Version: 0.1.5
Summary: A python package to decode Google News URLs.
Home-page: https://github.com/SSujitX/google-news-url-decoder
Author: Sujit Biswas
Author-email: ssujitxx@gmail.com
License: MIT
Classifier: Programming Language :: Python :: 3
Classifier: License :: OSI Approved :: MIT License
Classifier: Operating System :: OS Independent
Requires-Python: >=3.9
License-File: LICENSE
Requires-Dist: requests
Requires-Dist: selectolax
